mnemex/__init__.py
mnemex/background.py
mnemex/config.py
mnemex/context.py
mnemex/performance.py
mnemex/server.py
mnemex/backup/__init__.py
mnemex/backup/git_backup.py
mnemex/cli/__init__.py
mnemex/cli/migrate.py
mnemex/core/__init__.py
mnemex/core/clustering.py
mnemex/core/consolidation.py
mnemex/core/decay.py
mnemex/core/pagination.py
mnemex/core/review.py
mnemex/core/scoring.py
mnemex/integration/__init__.py
mnemex/integration/basic_memory.py
mnemex/security/__init__.py
mnemex/security/paths.py
mnemex/security/permissions.py
mnemex/security/secrets.py
mnemex/security/validators.py
mnemex/storage/__init__.py
mnemex/storage/jsonl_storage.py
mnemex/storage/ltm_index.py
mnemex/storage/maintenance.py
mnemex/storage/models.py
mnemex/tools/__init__.py
mnemex/tools/cluster.py
mnemex/tools/consolidate.py
mnemex/tools/create_relation.py
mnemex/tools/gc.py
mnemex/tools/observe.py
mnemex/tools/open_memories.py
mnemex/tools/performance.py
mnemex/tools/promote.py
mnemex/tools/read_graph.py
mnemex/tools/save.py
mnemex/tools/search.py
mnemex/tools/search_unified.py
mnemex/tools/touch.py
mnemex/vault/__init__.py
mnemex/vault/markdown_writer.py
mnemex_fastmcp-0.5.7.dist-info/METADATA
mnemex_fastmcp-0.5.7.dist-info/WHEEL
mnemex_fastmcp-0.5.7.dist-info/entry_points.txt
mnemex_fastmcp-0.5.7.dist-info/licenses/LICENSE
mnemex_fastmcp-0.5.7.dist-info/RECORD
