Metadata-Version: 2.4
Name: mnemex-fastmcp
Version: 0.5.7
Summary: Mnemex: Temporal memory management for AI assistants with human-like dynamics
Project-URL: Homepage, https://github.com/fastmcp-me/mnemex#readme
Project-URL: Repository, https://github.com/fastmcp-me/mnemex.git
Project-URL: Issues, https://github.com/fastmcp-me/mnemex/issues
Author: Mnemex
License: MIT
License-File: LICENSE
Keywords: ai,llm,mcp,memex,memory,mnemonic,temporal-decay
Requires-Python: >=3.10
Requires-Dist: gitpython>=3.1.40
Requires-Dist: markdown>=3.5.0
Requires-Dist: mcp>=1.2.0
Requires-Dist: pydantic>=2.0.0
Requires-Dist: python-dotenv>=1.0.0
Requires-Dist: python-frontmatter>=1.1.0
Provides-Extra: dev
Requires-Dist: mypy>=1.8.0; extra == 'dev'
Requires-Dist: pre-commit>=3.7.0; extra == 'dev'
Requires-Dist: pytest-asyncio>=0.23.0; extra == 'dev'
Requires-Dist: pytest-cov>=4.1.0; extra == 'dev'
Requires-Dist: pytest>=8.0.0; extra == 'dev'
Requires-Dist: ruff>=0.2.0; extra == 'dev'
Provides-Extra: embeddings
Requires-Dist: numpy>=1.24.0; extra == 'embeddings'
Requires-Dist: sentence-transformers>=2.0.0; extra == 'embeddings'
